fiscalsim_us
