Metadata-Version: 2.1
Name: fiscalsim-us
Version: 0.3.3
Summary: FiscalSim federal and state individual tax and benefit system for the US
Home-page: https://github.com/TheCGO/fiscalsim-us
Author: Richard W. Evans
Author-email: rick@abundance.institute
License: http://www.fsf.org/licensing/licenses/agpl-3.0.html
Keywords: tax benefit microsimulation fiscal state household individual personal
Classifier: Development Status :: 5 - Production/Stable
Classifier: License :: OSI Approved :: GNU Affero General Public License v3
Classifier: Operating System :: POSIX
Classifier: Programming Language :: Python
Classifier: Programming Language :: Python :: 3.10
Classifier: Topic :: Scientific/Engineering :: Information Analysis
Requires-Python: >=3.10, <3.12
Provides-Extra: dev
License-File: LICENSE
